[
  {
    "key": "1",
    "client": "Emily R.",
    "position": "Marketing Director",
    "testimonial": "We put our trust in Sunnyside and they delivered, making sure our needs were met and deadlines were always hit."
  },
  {
    "key": "2",
    "client": "Thomas S.",
    "position": "Chief Operating Officer",
    "testimonial": "Sunnyside’s enthusiasm coupled with their keen interest in our brand’s success made it a satisfying and enjoyable experience."
  },
  {
    "key": "3",
    "client": "Jennie F.",
    "position": "Business Owner",
    "testimonial": "Incredible end result! Our sales increased over 400% when we worked with Sunnyside. Highly recommended!"
  }
]
